sc_batch_run_retail/__init__.py
sc_batch_run_retail/main.py
sc_batch_run_retail/tests/__init__.py
sc_batch_run_retail/tests/sample_config/production.yml
sc_batch_run_retail_analysis-0.0.4.dist-info/LICENSE
sc_batch_run_retail_analysis-0.0.4.dist-info/METADATA
sc_batch_run_retail_analysis-0.0.4.dist-info/WHEEL
sc_batch_run_retail_analysis-0.0.4.dist-info/entry_points.txt
sc_batch_run_retail_analysis-0.0.4.dist-info/top_level.txt
sc_batch_run_retail_analysis-0.0.4.dist-info/RECORD
